Metadata-Version: 2.1
Name: distributions-saurav
Version: 0.3
Summary: Gaussian and Binomial Distribution
Author: Saurav Panchal
Author-email: saurav.panchal.08@gmail.com
